[
null,
{"id":1,"list":[{"code":111,"indent":0,"parameters":[0,51,0]},{"code":302,"indent":1,"parameters":[0,2,0,0,false]},{"code":605,"indent":1,"parameters":[0,3,0,0]},{"code":605,"indent":1,"parameters":[0,4,0,0]},{"code":605,"indent":1,"parameters":[0,5,0,0]},{"code":605,"indent":1,"parameters":[0,6,0,0]},{"code":605,"indent":1,"parameters":[0,7,0,0]},{"code":605,"indent":1,"parameters":[0,8,0,0]},{"code":605,"indent":1,"parameters":[0,9,0,0]},{"code":605,"indent":1,"parameters":[0,10,0,0]},{"code":0,"indent":1,"parameters":[]},{"code":411,"indent":0,"parameters":[]},{"code":111,"indent":1,"parameters":[0,33,0]},{"code":302,"indent":2,"parameters":[0,2,0,0,false]},{"code":605,"indent":2,"parameters":[0,3,0,0]},{"code":605,"indent":2,"parameters":[0,5,0,0]},{"code":605,"indent":2,"parameters":[0,6,0,0]},{"code":605,"indent":2,"parameters":[0,8,0,0]},{"code":605,"indent":2,"parameters":[0,9,0,0]},{"code":0,"indent":2,"parameters":[]},{"code":411,"indent":1,"parameters":[]},{"code":302,"indent":2,"parameters":[0,2,0,0,false]},{"code":605,"indent":2,"parameters":[0,5,0,0]},{"code":605,"indent":2,"parameters":[0,8,0,0]},{"code":605,"indent":2,"parameters":[0,9,0,0]},{"code":0,"indent":2,"parameters":[]},{"code":412,"indent":1,"parameters":[]},{"code":0,"indent":1,"parameters":[]},{"code":412,"indent":0,"parameters":[]},{"code":0,"indent":0,"parameters":[]}],"name":"道具屋","switchId":1,"trigger":0},
{"id":2,"list":[{"code":111,"indent":0,"parameters":[0,40,0]},{"code":302,"indent":1,"parameters":[0,21,0,0,false]},{"code":605,"indent":1,"parameters":[0,22,0,0]},{"code":605,"indent":1,"parameters":[0,23,0,0]},{"code":605,"indent":1,"parameters":[0,24,0,0]},{"code":605,"indent":1,"parameters":[0,25,0,0]},{"code":605,"indent":1,"parameters":[0,26,0,0]},{"code":605,"indent":1,"parameters":[0,27,0,0]},{"code":605,"indent":1,"parameters":[0,28,0,0]},{"code":605,"indent":1,"parameters":[0,29,0,0]},{"code":605,"indent":1,"parameters":[0,30,0,0]},{"code":605,"indent":1,"parameters":[0,31,0,0]},{"code":605,"indent":1,"parameters":[0,32,0,0]},{"code":605,"indent":1,"parameters":[0,33,0,0]},{"code":605,"indent":1,"parameters":[0,34,0,0]},{"code":605,"indent":1,"parameters":[0,35,0,0]},{"code":605,"indent":1,"parameters":[0,36,0,0]},{"code":0,"indent":1,"parameters":[]},{"code":411,"indent":0,"parameters":[]},{"code":302,"indent":1,"parameters":[0,21,0,0,false]},{"code":605,"indent":1,"parameters":[0,23,0,0]},{"code":605,"indent":1,"parameters":[0,25,0,0]},{"code":605,"indent":1,"parameters":[0,27,0,0]},{"code":605,"indent":1,"parameters":[0,29,0,0]},{"code":605,"indent":1,"parameters":[0,31,0,0]},{"code":605,"indent":1,"parameters":[0,33,0,0]},{"code":605,"indent":1,"parameters":[0,35,0,0]},{"code":0,"indent":1,"parameters":[]},{"code":412,"indent":0,"parameters":[]},{"code":0,"indent":0,"parameters":[]}],"name":"強化アイテム屋","switchId":1,"trigger":0},
{"id":3,"list":[{"code":111,"indent":0,"parameters":[0,60,0]},{"code":302,"indent":1,"parameters":[1,2,0,0,false]},{"code":605,"indent":1,"parameters":[1,3,0,0]},{"code":605,"indent":1,"parameters":[1,4,0,0]},{"code":605,"indent":1,"parameters":[1,5,0,0]},{"code":605,"indent":1,"parameters":[1,6,0,0]},{"code":605,"indent":1,"parameters":[1,7,0,0]},{"code":605,"indent":1,"parameters":[1,8,0,0]},{"code":605,"indent":1,"parameters":[1,9,0,0]},{"code":605,"indent":1,"parameters":[1,10,0,0]},{"code":605,"indent":1,"parameters":[2,2,0,0]},{"code":605,"indent":1,"parameters":[2,3,0,0]},{"code":605,"indent":1,"parameters":[2,4,0,0]},{"code":605,"indent":1,"parameters":[2,6,0,0]},{"code":605,"indent":1,"parameters":[2,7,0,0]},{"code":605,"indent":1,"parameters":[2,8,0,0]},{"code":605,"indent":1,"parameters":[2,10,0,0]},{"code":605,"indent":1,"parameters":[2,11,0,0]},{"code":605,"indent":1,"parameters":[2,12,0,0]},{"code":605,"indent":1,"parameters":[2,14,0,0]},{"code":605,"indent":1,"parameters":[2,15,0,0]},{"code":605,"indent":1,"parameters":[2,16,0,0]},{"code":605,"indent":1,"parameters":[2,18,0,0]},{"code":605,"indent":1,"parameters":[2,19,0,0]},{"code":605,"indent":1,"parameters":[2,20,0,0]},{"code":605,"indent":1,"parameters":[2,21,0,0]},{"code":605,"indent":1,"parameters":[2,22,0,0]},{"code":605,"indent":1,"parameters":[2,23,0,0]},{"code":605,"indent":1,"parameters":[2,24,0,0]},{"code":605,"indent":1,"parameters":[2,25,0,0]},{"code":0,"indent":1,"parameters":[]},{"code":411,"indent":0,"parameters":[]},{"code":111,"indent":1,"parameters":[0,40,0]},{"code":302,"indent":2,"parameters":[1,2,0,0,false]},{"code":605,"indent":2,"parameters":[1,3,0,0]},{"code":605,"indent":2,"parameters":[1,5,0,0]},{"code":605,"indent":2,"parameters":[1,6,0,0]},{"code":605,"indent":2,"parameters":[1,8,0,0]},{"code":605,"indent":2,"parameters":[1,9,0,0]},{"code":605,"indent":2,"parameters":[2,2,0,0]},{"code":605,"indent":2,"parameters":[2,3,0,0]},{"code":605,"indent":2,"parameters":[2,6,0,0]},{"code":605,"indent":2,"parameters":[2,7,0,0]},{"code":605,"indent":2,"parameters":[2,10,0,0]},{"code":605,"indent":2,"parameters":[2,11,0,0]},{"code":605,"indent":2,"parameters":[2,14,0,0]},{"code":605,"indent":2,"parameters":[2,15,0,0]},{"code":605,"indent":2,"parameters":[2,18,0,0]},{"code":605,"indent":2,"parameters":[2,19,0,0]},{"code":605,"indent":2,"parameters":[2,20,0,0]},{"code":605,"indent":2,"parameters":[2,21,0,0]},{"code":605,"indent":2,"parameters":[2,22,0,0]},{"code":605,"indent":2,"parameters":[2,23,0,0]},{"code":605,"indent":2,"parameters":[2,24,0,0]},{"code":605,"indent":2,"parameters":[2,25,0,0]},{"code":0,"indent":2,"parameters":[]},{"code":411,"indent":1,"parameters":[]},{"code":111,"indent":2,"parameters":[0,33,0]},{"code":302,"indent":3,"parameters":[1,2,0,0,false]},{"code":605,"indent":3,"parameters":[1,3,0,0]},{"code":605,"indent":3,"parameters":[1,5,0,0]},{"code":605,"indent":3,"parameters":[1,6,0,0]},{"code":605,"indent":3,"parameters":[1,8,0,0]},{"code":605,"indent":3,"parameters":[1,9,0,0]},{"code":605,"indent":3,"parameters":[2,2,0,0]},{"code":605,"indent":3,"parameters":[2,3,0,0]},{"code":605,"indent":3,"parameters":[2,6,0,0]},{"code":605,"indent":3,"parameters":[2,7,0,0]},{"code":605,"indent":3,"parameters":[2,10,0,0]},{"code":605,"indent":3,"parameters":[2,11,0,0]},{"code":605,"indent":3,"parameters":[2,14,0,0]},{"code":605,"indent":3,"parameters":[2,15,0,0]},{"code":605,"indent":3,"parameters":[2,18,0,0]},{"code":605,"indent":3,"parameters":[2,20,0,0]},{"code":605,"indent":3,"parameters":[2,22,0,0]},{"code":605,"indent":3,"parameters":[2,24,0,0]},{"code":0,"indent":3,"parameters":[]},{"code":411,"indent":2,"parameters":[]},{"code":302,"indent":3,"parameters":[1,2,0,0,false]},{"code":605,"indent":3,"parameters":[1,5,0,0]},{"code":605,"indent":3,"parameters":[1,8,0,0]},{"code":605,"indent":3,"parameters":[2,2,0,0]},{"code":605,"indent":3,"parameters":[2,6,0,0]},{"code":605,"indent":3,"parameters":[2,10,0,0]},{"code":605,"indent":3,"parameters":[2,14,0,0]},{"code":605,"indent":3,"parameters":[2,18,0,0]},{"code":605,"indent":3,"parameters":[2,20,0,0]},{"code":605,"indent":3,"parameters":[2,22,0,0]},{"code":605,"indent":3,"parameters":[2,24,0,0]},{"code":0,"indent":3,"parameters":[]},{"code":412,"indent":2,"parameters":[]},{"code":0,"indent":2,"parameters":[]},{"code":412,"indent":1,"parameters":[]},{"code":0,"indent":1,"parameters":[]},{"code":412,"indent":0,"parameters":[]},{"code":0,"indent":0,"parameters":[]}],"name":"装備屋","switchId":1,"trigger":0},
{"id":4,"list":[{"code":302,"indent":0,"parameters":[2,41,0,0,false]},{"code":605,"indent":0,"parameters":[2,42,0,0]},{"code":605,"indent":0,"parameters":[2,43,0,0]},{"code":605,"indent":0,"parameters":[2,44,0,0]},{"code":605,"indent":0,"parameters":[2,45,0,0]},{"code":605,"indent":0,"parameters":[2,46,0,0]},{"code":605,"indent":0,"parameters":[2,47,0,0]},{"code":605,"indent":0,"parameters":[2,48,0,0]},{"code":605,"indent":0,"parameters":[2,49,0,0]},{"code":605,"indent":0,"parameters":[2,50,0,0]},{"code":605,"indent":0,"parameters":[2,51,0,0]},{"code":605,"indent":0,"parameters":[2,52,0,0]},{"code":605,"indent":0,"parameters":[2,53,0,0]},{"code":605,"indent":0,"parameters":[2,54,0,0]},{"code":605,"indent":0,"parameters":[2,55,0,0]},{"code":605,"indent":0,"parameters":[2,56,0,0]},{"code":605,"indent":0,"parameters":[2,57,0,0]},{"code":605,"indent":0,"parameters":[2,58,0,0]},{"code":605,"indent":0,"parameters":[2,59,0,0]},{"code":605,"indent":0,"parameters":[2,60,0,0]},{"code":605,"indent":0,"parameters":[2,61,0,0]},{"code":605,"indent":0,"parameters":[2,62,0,0]},{"code":605,"indent":0,"parameters":[2,63,0,0]},{"code":0,"indent":0,"parameters":[]}],"name":"アクセサリ屋","switchId":1,"trigger":0},
{"id":5,"list":[{"code":111,"indent":0,"parameters":[0,3,0]},{"code":0,"indent":1,"parameters":[]},{"code":411,"indent":0,"parameters":[]},{"code":111,"indent":1,"parameters":[0,34,0]},{"code":201,"indent":2,"parameters":[0,7,17,19,2,0]},{"code":0,"indent":2,"parameters":[]},{"code":411,"indent":1,"parameters":[]},{"code":111,"indent":2,"parameters":[0,28,0]},{"code":201,"indent":3,"parameters":[0,12,4,4,2,0]},{"code":0,"indent":3,"parameters":[]},{"code":411,"indent":2,"parameters":[]},{"code":201,"indent":3,"parameters":[0,7,17,19,2,0]},{"code":0,"indent":3,"parameters":[]},{"code":412,"indent":2,"parameters":[]},{"code":0,"indent":2,"parameters":[]},{"code":412,"indent":1,"parameters":[]},{"code":0,"indent":1,"parameters":[]},{"code":412,"indent":0,"parameters":[]},{"code":101,"indent":0,"parameters":["main1",2,0,2]},{"code":401,"indent":0,"parameters":["酒居："]},{"code":401,"indent":0,"parameters":["不覚を取ったな..."]},{"code":401,"indent":0,"parameters":["次から気をつけよう。"]},{"code":0,"indent":0,"parameters":[]}],"name":"敗北","switchId":1,"trigger":0},
{"id":6,"list":[{"code":122,"indent":0,"parameters":[1,1,0,3,3,1,9]},{"code":122,"indent":0,"parameters":[1,1,4,0,60]},{"code":122,"indent":0,"parameters":[1,1,1,0,2]},{"code":312,"indent":0,"parameters":[0,1,0,1,1]},{"code":122,"indent":0,"parameters":[1,1,0,3,3,2,9]},{"code":122,"indent":0,"parameters":[1,1,4,0,60]},{"code":122,"indent":0,"parameters":[1,1,1,0,2]},{"code":312,"indent":0,"parameters":[0,2,0,1,1]},{"code":122,"indent":0,"parameters":[1,1,0,3,3,3,9]},{"code":122,"indent":0,"parameters":[1,1,4,0,60]},{"code":122,"indent":0,"parameters":[1,1,1,0,2]},{"code":312,"indent":0,"parameters":[0,3,0,1,1]},{"code":122,"indent":0,"parameters":[1,1,0,3,3,4,9]},{"code":122,"indent":0,"parameters":[1,1,4,0,60]},{"code":122,"indent":0,"parameters":[1,1,1,0,2]},{"code":312,"indent":0,"parameters":[0,4,0,1,1]},{"code":0,"indent":0,"parameters":[]}],"name":"ＭＰ回復","switchId":1,"trigger":0},
{"id":7,"list":[{"code":0,"indent":0,"parameters":[]}],"name":"","switchId":1,"trigger":0},
{"id":8,"list":[{"code":0,"indent":0,"parameters":[]}],"name":"","switchId":1,"trigger":0},
{"id":9,"list":[{"code":0,"indent":0,"parameters":[]}],"name":"","switchId":1,"trigger":0},
{"id":10,"list":[{"code":0,"indent":0,"parameters":[]}],"name":"","switchId":1,"trigger":0}
]